probdists/Binomialdistribution.py
probdists/Gaussiandistribution.py
probdists/Generaldistribution.py
probdists/__init__.py
probdists/numbers.txt
probdists/numbers_binomial.txt
probdists-1.9.dist-info/LICENCE.txt
probdists-1.9.dist-info/METADATA
probdists-1.9.dist-info/WHEEL
probdists-1.9.dist-info/top_level.txt
probdists-1.9.dist-info/RECORD
