Metadata-Version: 2.1
Name: probdists
Version: 1.9
Summary: Python Package for modelling Gaussian and Binomial distributions
Home-page: https://github.com/hot9cups/probdists
Author: Ayush Modi
Author-email: hot9cups@yahoo.in
License: UNKNOWN
Platform: UNKNOWN
Classifier: Programming Language :: Python :: 3
Classifier: License :: OSI Approved :: MIT License
Classifier: Operating System :: OS Independent
Requires-Python: >=3.6
Requires-Dist: matplotlib
